editor/__init__.py
editor/canvas_renderer.py
editor/config.py
editor/controller.py
editor/critic_change.py
editor/critic_parser.py
editor/critic_table.py
editor/document_metadata.py
editor/main.py
editor/markdown_canvas.py
editor/markdown_canvas_integration.py
editor/markdown_parser.py
editor/metadata_dialog.py
editor/model.py
editor/render_styles.py
editor/typora_theme_loader.py
editor/view.py
editor/full_typora_theme_support/__init__.py
editor/full_typora_theme_support/css_properties.py
editor/full_typora_theme_support/css_utils.py
editor/full_typora_theme_support/enhanced_canvas.py
editor/full_typora_theme_support/enhanced_canvas_renderer.py
editor/full_typora_theme_support/syntax_highlighter.py
editor/full_typora_theme_support/theme_loader.py
editor/theme_editor/__init__.py
editor/theme_editor/config.py
editor/theme_editor/icons.py
editor/theme_editor/property_editor_dialog.py
editor/theme_editor/theme_editor_window.py
editor/theme_editor/theme_manager.py
editor/theme_editor/samples/comprehensive.md
editor/theme_editor/samples/tables.md
editor/theme_editor/ui/__init__.py
editor/theme_editor/widgets/__init__.py
scriptum_simplex-100.0.dist-info/METADATA
scriptum_simplex-100.0.dist-info/WHEEL
scriptum_simplex-100.0.dist-info/entry_points.txt
scriptum_simplex-100.0.dist-info/top_level.txt
scriptum_simplex-100.0.dist-info/RECORD
