Metadata-Version: 2.1
Name: scriptum-simplex
Version: 100.0
Summary: Markdown editor with CriticMarkup support and Typora theme editor
Home-page: https://sourceforge.net/projects/scriptum-simplex/
Author: Scriptum Simplex Project
Author-email: Scriptum Simplex Project <scriptum.simplex@example.com>
License: MIT
Project-URL: Homepage, https://sourceforge.net/projects/scriptum-simplex/
Project-URL: Documentation, https://sourceforge.net/p/scriptum-simplex/wiki/
Project-URL: Repository, https://sourceforge.net/p/scriptum-simplex/code/
Project-URL: Bug Tracker, https://sourceforge.net/p/scriptum-simplex/tickets/
Keywords: markdown,editor,criticmarkup,change-tracking,typora,themes,css-editor,document-editing,collaborative-editing,gui,tkinter
Classifier: Development Status :: 5 - Production/Stable
Classifier: Intended Audience :: Developers
Classifier: Intended Audience :: Education
Classifier: Intended Audience :: End Users/Desktop
Classifier: Intended Audience :: Science/Research
Classifier: Topic :: Text Editors
Classifier: Topic :: Office/Business
Classifier: Topic :: Documentation
Classifier: License :: OSI Approved :: MIT License
Classifier: Programming Language :: Python :: 3
Classifier: Programming Language :: Python :: 3.11
Classifier: Programming Language :: Python :: 3.12
Classifier: Operating System :: OS Independent
Classifier: Environment :: X11 Applications
Classifier: Environment :: Win32 (MS Windows)
Classifier: Environment :: MacOS X
Requires-Python: >=3.11
Requires-Dist: ttkbootstrap (>=1.10.1)
Requires-Dist: markdown (>=3.4.0)
Requires-Dist: mistune (>=3.0.0)
Requires-Dist: tinycss2 (>=1.2.1)
Requires-Dist: cssselect2 (>=0.7.0)
Requires-Dist: webencodings (>=0.5.1)
Provides-Extra: build
Requires-Dist: pyinstaller (>=5.13.0) ; extra == 'build'
Requires-Dist: wheel (>=0.41.0) ; extra == 'build'
Requires-Dist: twine (>=4.0.0) ; extra == 'build'
Provides-Extra: dev
Requires-Dist: pytest (>=7.4.0) ; extra == 'dev'
Requires-Dist: pytest-cov (>=4.1.0) ; extra == 'dev'
Requires-Dist: mypy (>=1.5.0) ; extra == 'dev'
Requires-Dist: flake8 (>=6.1.0) ; extra == 'dev'
Requires-Dist: black (>=23.7.0) ; extra == 'dev'
